COPYING.txt
MANIFEST.in
README.md
setup.cfg
setup.py
aurelix/__init__.py
aurelix/api.py
aurelix/cli.py
aurelix/client.py
aurelix/dependencies.py
aurelix/exc.py
aurelix/schema.py
aurelix/settings.py
aurelix/state.py
aurelix/utils.py
aurelix.egg-info/PKG-INFO
aurelix.egg-info/SOURCES.txt
aurelix.egg-info/dependency_links.txt
aurelix.egg-info/entry_points.txt
aurelix.egg-info/not-zip-safe
aurelix.egg-info/requires.txt
aurelix.egg-info/top_level.txt
aurelix/crud/__init__.py
aurelix/crud/base.py
aurelix/crud/dependencies.py
aurelix/crud/lowcode.py
aurelix/crud/routes.py
aurelix/crud/sqla.py