Metadata-Version: 2.1
Name: aurelix
Version: 0.1
Summary: Low code API framework based on Dectate and FastAPI
Home-page: 
Author: Izhar Firdaus
Author-email: kagesenshi.87@gmail.com
License: LGPLv3
Provides-Extra: server
Provides-Extra: all
License-File: COPYING.txt
